pytest_llmeval/__init__.py
pytest_llmeval/plugin.py
pytest_llmeval-0.0.0.dist-info/licenses/LICENSE
pytest_llmeval-0.0.0.dist-info/METADATA
pytest_llmeval-0.0.0.dist-info/WHEEL
pytest_llmeval-0.0.0.dist-info/entry_points.txt
pytest_llmeval-0.0.0.dist-info/top_level.txt
pytest_llmeval-0.0.0.dist-info/RECORD
