Metadata-Version: 2.4
Name: pytest-llmeval
Version: 0.0.0
Summary: A pytest plugin to evaluate/benchmark LLM prompts
Author-email: Kevin Schaul <kevin.schaul@gmail.com>
Maintainer-email: Kevin Schaul <kevin.schaul@gmail.com>
License: 
Project-URL: Repository, https://github.com/kevinschaul/pytest-llmeval
Classifier: Framework :: Pytest
Classifier: Development Status :: 4 - Beta
Classifier: Intended Audience :: Developers
Classifier: Topic :: Software Development :: Testing
Classifier: Operating System :: OS Independent
Classifier: Programming Language :: Python
Classifier: Programming Language :: Python :: 3.8
Classifier: Programming Language :: Python :: 3.9
Classifier: Programming Language :: Python :: 3.10
Classifier: Programming Language :: Python :: 3.11
Classifier: Programming Language :: Python :: 3.12
Classifier: Programming Language :: Python :: 3 :: Only
Classifier: Programming Language :: Python :: Implementation :: CPython
Classifier: Programming Language :: Python :: Implementation :: PyPy
Classifier: License :: OSI Approved :: MIT License
Requires-Python: >=3.9
License-File: LICENSE
Requires-Dist: pytest>=6.2.0
Requires-Dist: scikit-learn>=1.3.2
Dynamic: license-file
